opentrans/__init__.py
opentrans/cache_manager.py
opentrans/hasher.py
opentrans/main.py
opentrans/settings.py
opentrans/translator.py
opentrans-0.1.1.dist-info/METADATA
opentrans-0.1.1.dist-info/WHEEL
opentrans-0.1.1.dist-info/entry_points.txt
opentrans-0.1.1.dist-info/licenses/LICENSE.md
opentrans-0.1.1.dist-info/RECORD
