Metadata-Version: 2.4
Name: opentrans
Version: 0.1.1
Summary: A directory-preserving AI translator using Ollama.
Project-URL: Homepage, https://github.com/RainStorm108/opentrans
Project-URL: Documentation, https://rainstorm108.github.io/OpenTrans/
Project-URL: Issues, https://github.com/RainStorm108/opentrans/issues
Author: Hydrangea
License: MIT
License-File: LICENSE.md
Keywords: ai,automation,llm,ollama,translation
Classifier: Development Status :: 4 - Beta
Classifier: Intended Audience :: Developers
Classifier: License :: OSI Approved :: MIT License
Classifier: Operating System :: OS Independent
Classifier: Programming Language :: Python :: 3
Classifier: Programming Language :: Python :: 3.9
Classifier: Programming Language :: Python :: 3.10
Classifier: Programming Language :: Python :: 3.11
Classifier: Topic :: Text Processing :: Linguistic
Requires-Python: >=3.9
Requires-Dist: click
Requires-Dist: ollama>=0.1.0
Requires-Dist: pydantic
Requires-Dist: pydantic-settings
Requires-Dist: pyyaml
Requires-Dist: tqdm>=4.66.0
